MANIFEST.in
README.md
cast_from_env.py
setup.py
test.py
cast_from_env.egg-info/PKG-INFO
cast_from_env.egg-info/SOURCES.txt
cast_from_env.egg-info/dependency_links.txt
cast_from_env.egg-info/top_level.txt