Metadata-Version: 2.1
Name: cast-from-env
Version: 0.0.5
Summary: Get and cast environment variables
Home-page: http://github.com/Media-Platforms/cast-from-env
Author: Nic Wolff
Author-email: nwolff@hearst.com
License: MIT
Platform: UNKNOWN
